shipzo_divide/__init__.py
shipzo_divide/shipzo_divide.py
shipzo_divide-0.1.1.dist-info/METADATA
shipzo_divide-0.1.1.dist-info/WHEEL
shipzo_divide-0.1.1.dist-info/entry_points.txt
shipzo_divide-0.1.1.dist-info/top_level.txt
shipzo_divide-0.1.1.dist-info/RECORD
