Metadata-Version: 2.1
Name: shipzo_divide
Version: 0.1.1
Summary: Default template for PDM package
Author-email: rlaehgus97 <starkim625@gmail.com>
License: MIT
Project-URL: Homepage, https://github.com/rlaehgus97/shipzo_divide
Project-URL: Issues, https://github.com/rlaehgus97/shipzo_divide/issues
Requires-Python: >=3.9
